<?xml version="1.0" encoding="UTF-8"?>

<lifecycleMappingMetadata>

	<pluginExecutions>

		<pluginExecution>
			<pluginExecutionFilter>
				<groupId>org.apache.felix</groupId>
				<artifactId>maven-scr-plugin</artifactId>
				<versionRange>[0,)</versionRange>
				<goals>
					<goal>scr</goal>
				</goals>
			</pluginExecutionFilter>
			<action>
				<configurator>
					<id>com.carrotgarden.m2e.config.Config</id>
				</configurator>
			</action>
		</pluginExecution>

		<pluginExecution>
			<pluginExecutionFilter>
				<groupId>org.apache.felix</groupId>
				<artifactId>maven-bundle-plugin</artifactId>
				<versionRange>[0,)</versionRange>
				<goals>
					<goal>manifest</goal>
				</goals>
			</pluginExecutionFilter>
			<action>
				<configurator>
					<id>com.carrotgarden.m2e.config.Config</id>
				</configurator>
			</action>
		</pluginExecution>

	</pluginExecutions>

</lifecycleMappingMetadata>
